[{"user_id":4854500877487,"comment_id":10154973012811600,"date":"2017-01-06","message":"God bless them.","prediction":1,"predicted_probs":0.821,"user_ideo":0.393,"ideology_label":1,"political":"no","topic_number":203,"partisan":"no","ideology":"right","order_index":1,"json_serial_number":976},{"user_id":1112443558829468,"comment_id":10153163486675667,"date":"2015-11-16","message":"I can't understand a word DT says with that golden spoon in his mouth!!! Grrrrrrr!!!","prediction":0,"predicted_probs":0.0422,"user_ideo":-0.642,"ideology_label":0,"political":"no","topic_number":165,"partisan":"regular","ideology":"left","order_index":2,"json_serial_number":976},{"user_id":10207993394085552,"comment_id":581753868657416,"date":"2016-03-09","message":"Thanks . Thanks.","prediction":0,"predicted_probs":0.313,"user_ideo":0.6853,"ideology_label":1,"political":"yes","topic_number":107,"partisan":"regular","ideology":"right","order_index":3,"json_serial_number":976},{"user_id":10202097693720474,"comment_id":1002335113209656,"date":"2016-11-21","message":"Sadly a portion of our country are greedy, rude, discriminatory and self serving. If the word military was mentioned at all, everyone should have stood and clapped. But, if he got himself killed, and not survived, as I heard lately, .......then.... Our world will never be the same. People who boo anything are low class to me.","prediction":0,"predicted_probs":0.0441,"user_ideo":-0.4926,"ideology_label":0,"political":"no","topic_number":205,"partisan":"no","ideology":"left","order_index":4,"json_serial_number":976},{"user_id":1720206901562792,"comment_id":10153981241138984,"date":"2015-12-28","message":"This card is only hard to read if your a moron, I'm sure he won't make that mistake again, but if it was me, I wouldn't have him back.","prediction":1,"predicted_probs":0.8862,"user_ideo":0.8306,"ideology_label":1,"political":"no","topic_number":247,"partisan":"extreme","ideology":"right","order_index":5,"json_serial_number":976},{"user_id":10209787726910816,"comment_id":10155025517711162,"date":"2016-12-22","message":"Another liberal Democrat being racist","prediction":1,"predicted_probs":0.9991,"user_ideo":0.4025,"ideology_label":1,"political":"yes","topic_number":236,"partisan":"leaning","ideology":"right","order_index":6,"json_serial_number":976},{"user_id":10157515016265105,"comment_id":10154336972974117,"date":"2017-01-17","message":"I was hoping that charlatan was already dead...","prediction":0,"predicted_probs":0.1447,"user_ideo":0.4565,"ideology_label":1,"political":"yes","topic_number":13,"partisan":"no","ideology":"right","order_index":7,"json_serial_number":976},{"user_id":10209215890047240,"comment_id":10154178545834497,"date":"2016-04-01","message":"DJ's speech cut short, since the government requires him to spin 50 minutes of music every hour, all day long.","prediction":0,"predicted_probs":0.1616,"user_ideo":-0.5298,"ideology_label":0,"political":"no","topic_number":225,"partisan":"regular","ideology":"left","order_index":8,"json_serial_number":976},{"user_id":10155129050233135,"comment_id":999232613440125,"date":"2015-01-19","message":"Good reason for disqualification","prediction":0,"predicted_probs":0.4345,"user_ideo":0.3637,"ideology_label":1,"political":"no","topic_number":247,"partisan":"leaning","ideology":"right","order_index":9,"json_serial_number":976},{"user_id":1162443530469863,"comment_id":1407593579280195,"date":"2017-01-23","message":"This is awesome! May God bless you Ofc. Tutor. Father God we lift up Ofc. Tutor to you. In the name of Jesus we decree a fast wind on her back and decree protection of her legs, joints and feet. We pray for a safe Marathon and we pray that Ofc. Tutor receives your strength and Holy Spirit and the energy. We bind the devil from any and all attempts to block this and declare that the Holy Spirit is with all who participate. We thank you in advance Lord God and believe it's done in Jesus mighty name amen","prediction":1,"predicted_probs":0.896,"user_ideo":0.3044,"ideology_label":1,"political":"no","topic_number":95,"partisan":"no","ideology":"right","order_index":10,"json_serial_number":976},{"user_id":10153805297736297,"comment_id":10154152495194062,"date":"2015-07-23","message":"Who is saying only white people are racist???????????????? Projecting, much?","prediction":0,"predicted_probs":0.0912,"user_ideo":-0.479,"ideology_label":0,"political":"yes","topic_number":236,"partisan":"leaning","ideology":"left","order_index":11,"json_serial_number":976},{"user_id":1180551978662938,"comment_id":10154099547864166,"date":"2016-04-18","message":"And here we go...","prediction":0,"predicted_probs":0.216,"user_ideo":0.4874,"ideology_label":1,"political":"yes","topic_number":55,"partisan":"no","ideology":"right","order_index":12,"json_serial_number":976},{"user_id":1771008423110918,"comment_id":10153056348398145,"date":"2015-05-14","message":"Game over","prediction":1,"predicted_probs":0.5842,"user_ideo":-0.4722,"ideology_label":0,"political":"no","topic_number":160,"partisan":"leaning","ideology":"left","order_index":13,"json_serial_number":976},{"user_id":1218346988216656,"comment_id":581402072011742,"date":"2016-01-12","message":"My admiration for my President just gets bigger every day!","prediction":0,"predicted_probs":0.0666,"user_ideo":-0.4617,"ideology_label":0,"political":"yes","topic_number":172,"partisan":"no","ideology":"left","order_index":14,"json_serial_number":976},{"user_id":10201872326206275,"comment_id":10154815150771756,"date":"2016-09-30","message":"Glad for him, but he has the intelligence of one of the rocks he's climbed, poor dear.","prediction":0,"predicted_probs":0.1043,"user_ideo":-0.805,"ideology_label":0,"political":"no","topic_number":95,"partisan":"extreme","ideology":"left","order_index":15,"json_serial_number":976},{"user_id":10206491183339982,"comment_id":10154499449941509,"date":"2016-02-25","message":"In a stall or a urinal? A stall is private, you don't know who has what.","prediction":0,"predicted_probs":0.1028,"user_ideo":-0.6517,"ideology_label":0,"political":"yes","topic_number":55,"partisan":"regular","ideology":"left","order_index":16,"json_serial_number":976},{"user_id":1376035449074704,"comment_id":10153511930723188,"date":"2015-07-27","message":"Hang in there. Trust me if you keep it up in a couple of months you will notice the difference. Unfortunately, we get discouraged quickly---big struggle for sure.","prediction":0,"predicted_probs":0.2528,"user_ideo":0.6014,"ideology_label":1,"political":"no","topic_number":102,"partisan":"regular","ideology":"right","order_index":17,"json_serial_number":976},{"user_id":10210927927780993,"comment_id":1894572497421769,"date":"2017-01-09","message":"Wow!!!!","prediction":0,"predicted_probs":0.3835,"user_ideo":0.4783,"ideology_label":1,"political":"yes","topic_number":210,"partisan":"leaning","ideology":"right","order_index":18,"json_serial_number":976},{"user_id":1247771355241715,"comment_id":1054832827890522,"date":"2015-06-11","message":"Hate is hate, evil is evil, people like this man are the problem. If it wasn't Muslims it would be someone else.","prediction":0,"predicted_probs":0.3348,"user_ideo":-0.752,"ideology_label":0,"political":"yes","topic_number":163,"partisan":"extreme","ideology":"left","order_index":19,"json_serial_number":976},{"user_id":10154211754354145,"comment_id":1478589588834523,"date":"2016-10-20","message":"This is just ridiculous. 6 percent. That's almost 90.","prediction":1,"predicted_probs":0.6637,"user_ideo":0.8648,"ideology_label":1,"political":"yes","topic_number":214,"partisan":"extreme","ideology":"right","order_index":20,"json_serial_number":976}]
