[{"user_id":10210311912377961,"comment_id":10154616263621729,"date":"2016-04-29","message":"She made it through Ranger School without special treatment. Give that warrior her due...she earned it.","prediction":1,"predicted_probs":0.6853,"user_ideo":0.8017,"ideology_label":1,"partisan":"partisan","political":"yes","topic_number":252,"index":1},{"user_id":1074295182655572,"comment_id":638823922908867,"date":"2016-11-26","message":"Mercy is it not so sad seems like anytime someone lets a fart now days it offends somone or they just gotta sue them this us getting old mercy folks stay your butts at home if your going to wear your feelings on your sleeves and quit being cry baby tattle tales !!!","prediction":1,"predicted_probs":0.9977,"user_ideo":0.7071,"ideology_label":1,"partisan":"partisan","political":"no","topic_number":134,"index":2},{"user_id":1136255236432910,"comment_id":10153753653566409,"date":"2016-07-28","message":"And this surprises you why","prediction":1,"predicted_probs":0.7413,"user_ideo":-0.045,"ideology_label":0,"partisan":"non-partisan","political":"yes","topic_number":59,"index":3},{"user_id":10207067249028179,"comment_id":1457634990918824,"date":"2016-09-16","message":"That's meaningless rush","prediction":1,"predicted_probs":0.7673,"user_ideo":0.9375,"ideology_label":1,"partisan":"partisan","political":"no","topic_number":72,"index":4},{"user_id":10204626019610044,"comment_id":10156454902940354,"date":"2015-12-02","message":"Well if they are middle eastern men we won't see the president calling republican terrorists tonight on t.v..","prediction":1,"predicted_probs":0.9631,"user_ideo":0.813,"ideology_label":1,"partisan":"partisan","political":"yes","topic_number":233,"index":5},{"user_id":10154346762427836,"comment_id":10150693695359999,"date":"2015-11-13","message":"Me too...dang!","prediction":0,"predicted_probs":0.2534,"user_ideo":-0.4103,"ideology_label":0,"partisan":"non-partisan","political":"no","topic_number":32,"index":6},{"user_id":10157406200525454,"comment_id":10154508426724641,"date":"2016-09-22","message":"It's a very different situation. Stop playing devils advocate. Or if you're not, stop being a jerk.","prediction":0,"predicted_probs":0.1264,"user_ideo":-0.7822,"ideology_label":0,"partisan":"partisan","political":"yes","topic_number":137,"index":7},{"user_id":2084935668397543,"comment_id":10153715240606162,"date":"2015-09-12","message":"You are so right Tabby kurtz","prediction":1,"predicted_probs":0.8316,"user_ideo":-0.5852,"ideology_label":0,"partisan":"partisan","political":"no","topic_number":189,"index":8},{"user_id":1174445479242583,"comment_id":10153316309286336,"date":"2015-05-30","message":"Stupid Left Wing Liberal Moron! Mindless, Obamabot Zombie LOSER!","prediction":1,"predicted_probs":0.9994,"user_ideo":0.7539,"ideology_label":1,"partisan":"partisan","political":"yes","topic_number":78,"index":9},{"user_id":1758326524452373,"comment_id":10154811160458812,"date":"2016-09-21","message":", why would you wish harm on someone elses child. Gun owners should know what to do with their gun when the police are there.","prediction":0,"predicted_probs":0.1811,"user_ideo":0.2645,"ideology_label":1,"partisan":"non-partisan","political":"yes","topic_number":144,"index":10},{"user_id":10208724191615344,"comment_id":1296206870457846,"date":"2016-11-04","message":"Obama has lost his mind he's using the favorite strategy of the Democrats accuse the other person of everything you are doing and they're so stupid they think people still believe it. I can't wait to see him go","prediction":1,"predicted_probs":0.9994,"user_ideo":0.2197,"ideology_label":1,"partisan":"non-partisan","political":"yes","topic_number":38,"index":11},{"user_id":10154342055600320,"comment_id":10153232978501323,"date":"2015-04-11","message":"Well, water is a chemical.....","prediction":0,"predicted_probs":0.1197,"user_ideo":0.3557,"ideology_label":1,"partisan":"non-partisan","political":"no","topic_number":135,"index":12},{"user_id":10153916120715044,"comment_id":10153543507259753,"date":"2016-01-22","message":"Letitia Vasconcelos, please please please please please please please do this.","prediction":0,"predicted_probs":0.0322,"user_ideo":-0.3868,"ideology_label":0,"partisan":"non-partisan","political":"no","topic_number":79,"index":13},{"user_id":1024558844260446,"comment_id":10153222087310736,"date":"2016-02-08","message":"Just keep posting more evidence boys...makes it so much easier to uphold convictions.....","prediction":1,"predicted_probs":0.5582,"user_ideo":-0.3353,"ideology_label":0,"partisan":"non-partisan","political":"yes","topic_number":182,"index":14},{"user_id":10153624499457234,"comment_id":1778610402399878,"date":"2016-10-16","message":"Sign us up!!!!","prediction":0,"predicted_probs":0.2917,"user_ideo":-0.5204,"ideology_label":0,"partisan":"partisan","political":"no","topic_number":95,"index":15},{"user_id":658592804308964,"comment_id":10152800359526615,"date":"2015-05-22","message":"12.50 is better then 0$ sitting on ur butt at home","prediction":0,"predicted_probs":0.4617,"user_ideo":-0.2276,"ideology_label":0,"partisan":"non-partisan","political":"no","topic_number":75,"index":16},{"user_id":10208520378200313,"comment_id":10156285266525294,"date":"2015-10-22","message":"Keep it to yourself. Many of us knew how to keep our virginity in the old days --- that didn't men we weren't sexual. I agree that some of this fundamentalist stuff sexualizes the relationship between a Father and Daughter -- it's demeaning to a woman and makes her subservient. Wake up ladies.","prediction":0,"predicted_probs":0.0597,"user_ideo":-0.5768,"ideology_label":0,"partisan":"partisan","political":"no","topic_number":43,"index":17},{"user_id":10153618145226039,"comment_id":1039150246122315,"date":"2016-01-06","message":"That little man needs to be getting rid of.","prediction":1,"predicted_probs":0.6774,"user_ideo":0.8198,"ideology_label":1,"partisan":"partisan","political":"yes","topic_number":65,"index":18},{"user_id":10155866595023421,"comment_id":10153270999283124,"date":"2015-08-28","message":"Easier to get on rides at Disney World/Disneyland bc there are less kids! #AmazonSweepstakes","prediction":0,"predicted_probs":0.1837,"user_ideo":0.0326,"ideology_label":1,"partisan":"non-partisan","political":"no","topic_number":264,"index":19},{"user_id":383588295354810,"comment_id":10154354348597577,"date":"2016-06-29","message":"My question is why didn't Infowars have the Minutemen there and start shooting the illegals and arresting them by letting them go that are perpetuating the problem","prediction":1,"predicted_probs":0.9983,"user_ideo":-0.0914,"ideology_label":0,"partisan":"non-partisan","political":"yes","topic_number":88,"index":20}]
