[{"user_id":10207400155181709,"comment_id":10153272491281717,"date":"2016-01-21","message":"I was bi all my younger years. And still I love to see great asses on both, all","prediction":0,"predicted_probs":0.0592,"user_ideo":-0.5048,"ideology_label":0,"partisan_type":"partisan","split":0.14,"percentile":"1-20 percentile","order_index":1,"json_serial_number":415},{"user_id":10210226719210181,"comment_id":1073752092665262,"date":"2015-07-08","message":"They also had a video a year ago with kids reacting to same-sex marriage proposal's.","prediction":0,"predicted_probs":0.3682,"user_ideo":-0.463,"ideology_label":0,"partisan_type":"moderate","split":0.43,"percentile":"21-80 percentile","order_index":2,"json_serial_number":415},{"user_id":1463156923709770,"comment_id":986218024804585,"date":"2015-10-28","message":"I can't be happy that someone died, but if it was him or the lion? I'd rather it not be the lion.","prediction":0,"predicted_probs":0.1889,"user_ideo":-0.8468,"ideology_label":0,"partisan_type":"partisan","split":0.28,"percentile":"21-80 percentile","order_index":3,"json_serial_number":415},{"comment_id":10157677521025294,"date":"2016-10-05","message":"And now you want to act as a president. tooooo late go away. we don't need you. take your queen if that what she thinks of herself. better watch maybe you will be a grandpa the way your daughter is be having lol big lol what no golf ro bad, where were you when us americans needed you. good bye and good riddance.","prediction":1,"predicted_probs":0.9984,"partisan_type":"no_info","split":0.96,"percentile":"81-100 percentile","order_index":4,"json_serial_number":415},{"comment_id":10154661437999197,"date":"2016-11-10","message":"So stinkin cute!","prediction":0,"predicted_probs":0.3202,"partisan_type":"no_info","split":0.4,"percentile":"21-80 percentile","order_index":5,"json_serial_number":415},{"comment_id":10155177369800389,"date":"2015-01-21","message":"How about allowing women to meet men's income levels. He stated it right! We are in 2015","prediction":0,"predicted_probs":0.0607,"partisan_type":"no_info","split":0.14,"percentile":"1-20 percentile","order_index":6,"json_serial_number":415},{"user_id":10207608891409569,"comment_id":10154727316891162,"date":"2016-09-29","message":"Omg yes please","prediction":0,"predicted_probs":0.1835,"user_ideo":-0.2894,"ideology_label":0,"partisan_type":"moderate","split":0.28,"percentile":"21-80 percentile","order_index":7,"json_serial_number":415},{"user_id":10210403281067746,"comment_id":10154131536246438,"date":"2016-06-28","message":"He didn't lose anything. What makes you think he wanted to do what Warren is doing? Perhaps he has other plans for his summer, can we please wait until after the convention for this sort of baloney?","prediction":0,"predicted_probs":0.0169,"user_ideo":-0.5605,"ideology_label":0,"partisan_type":"partisan","split":0.07,"percentile":"1-20 percentile","order_index":8,"json_serial_number":415},{"user_id":10157357487550077,"comment_id":843158875780366,"date":"2015-02-05","message":"Yep , they voted for Oblunder .. Twice","prediction":1,"predicted_probs":0.9993,"user_ideo":0.7016,"ideology_label":1,"partisan_type":"partisan","split":0.98,"percentile":"81-100 percentile","order_index":9,"json_serial_number":415},{"user_id":10209038122888752,"comment_id":10153852469703690,"date":"2015-11-13","message":"Today was a shooting attack in Israel killed a father and son and a great fortune and the other children not to publish cnn and bbc chose not to not look at what the Muslims are doing for us in Israel. More than 10 hours to show the attack. Rejects it. And still believe they have a Palestinian people ... who had their memories be blessed.","prediction":1,"predicted_probs":0.9591,"user_ideo":0.259,"ideology_label":1,"partisan_type":"moderate","split":0.86,"percentile":"81-100 percentile","order_index":10,"json_serial_number":415},{"user_id":1180425565356354,"comment_id":10155229404554749,"date":"2017-01-30","message":"Trump is doing exactly what he promised Americans he would do if they were to elect him. Suck it up snowflakes it's democracy. The protests are of course from those who can't accept the result nor seem to have any concerns about Isreali citizens being barred entry from sixteen Muslim states. The level of double standards from these people is shocking.","prediction":1,"predicted_probs":0.9531,"user_ideo":0.0054,"ideology_label":1,"partisan_type":"moderate","split":0.85,"percentile":"81-100 percentile","order_index":11,"json_serial_number":415},{"comment_id":10154985413774641,"date":"2017-02-07","message":"Alternative lies","prediction":0,"predicted_probs":0.0059,"partisan_type":"no_info","split":0.04,"percentile":"1-20 percentile","order_index":12,"json_serial_number":415},{"user_id":184005622015908,"comment_id":10153713400325736,"date":"2016-09-14","message":"I have a granddaughter at that school. Used to be bell bottom or \"\"\"\"pegged\"\"\"\" jeans(anyone remember), piercings and bare midriff have been the target of dress codes too. Before then skirts above the knee. Every generation gets to experience this.. tell me how it disrupts the \"\"\"\"learning environment\"\"\"\" And I'm all ears","prediction":0,"predicted_probs":0.1021,"user_ideo":-0.2966,"ideology_label":0,"partisan_type":"moderate","split":0.19,"percentile":"1-20 percentile","order_index":13,"json_serial_number":415},{"user_id":1245934958758439,"comment_id":10154866122794614,"date":"2016-11-23","message":"look at the Great Generation. Kids as young as 14 took up the call to arms. Then came home worked hard and built a life for them and their children","prediction":1,"predicted_probs":0.9874,"user_ideo":0.6554,"ideology_label":1,"partisan_type":"partisan","split":0.91,"percentile":"81-100 percentile","order_index":14,"json_serial_number":415},{"user_id":10157946246785377,"comment_id":10153505705546116,"date":"2016-07-29","message":"And they are oh-so cozy with CNN. ITS RIGGED BY THE PATHETIC SUPERDELEGATES. Statistically it clinches the whole thing and misleads/confuses voters at every step. Sanders fought evil in the civil rights movement and evil of the corruption by refusing to endorse Clinton till he got superdelegate reform.","prediction":0,"predicted_probs":0.0028,"user_ideo":-0.4871,"ideology_label":0,"partisan_type":"moderate","split":0.03,"percentile":"1-20 percentile","order_index":15,"json_serial_number":415},{"comment_id":10156341394405389,"date":"2015-11-17","message":"All the Government has to do, buy Carnival Cruise Line, NO Crew just one Syrian Captain, put all this SandNiggers on bord, sail out of Miami and blow them up in the middle of the ocean.","prediction":1,"predicted_probs":0.989,"partisan_type":"no_info","split":0.91,"percentile":"81-100 percentile","order_index":16,"json_serial_number":415},{"user_id":10208183588932593,"comment_id":10153910338161509,"date":"2015-08-03","message":"We ARE going to destroy you, and all your kind! Be afraid, be VERY afraid.","prediction":0,"predicted_probs":0.3307,"user_ideo":-0.7992,"ideology_label":0,"partisan_type":"partisan","split":0.4,"percentile":"21-80 percentile","order_index":17,"json_serial_number":415},{"comment_id":10153085496661336,"date":"2015-03-22","message":"Al capones vault describes Gerardo's career in two words","prediction":1,"predicted_probs":0.5386,"partisan_type":"no_info","split":0.56,"percentile":"21-80 percentile","order_index":18,"json_serial_number":415}]
